sr_vulkan_model_realsr/__init__.py
sr_vulkan_model_realsr/hook-sr_vulkan_model_realsr.py
sr_vulkan_model_realsr/models/REALSR_DF2K_UP4X.bin
sr_vulkan_model_realsr/models/REALSR_DF2K_UP4X.param
sr_vulkan_model_realsr-1.0.1.dist-info/METADATA
sr_vulkan_model_realsr-1.0.1.dist-info/WHEEL
sr_vulkan_model_realsr-1.0.1.dist-info/entry_points.txt
sr_vulkan_model_realsr-1.0.1.dist-info/top_level.txt
sr_vulkan_model_realsr-1.0.1.dist-info/RECORD
